{"version":"1","myst":"1.6.0","references":[{"kind":"page","data":"/content/index.json","url":"/"},{"identifier":"instructors","kind":"heading","data":"/content/index.json","url":"/","implicit":true},{"kind":"page","data":"/content/netlogo.index.json","url":"/netlogo"},{"kind":"page","data":"/content/netlogo.coding.index.json","url":"/netlogo/coding"},{"kind":"page","data":"/content/netlogo.coding.agents.json","url":"/netlogo/coding/agents"},{"kind":"page","data":"/content/intro.a-whatisamodel.json","url":"/intro/a-whatisamodel"}]}